trawler/__init__.py
trawler/agent/jobs.py
trawler/agent/main.py
trawler/graph.py
trawler/ontology.py
trawler/schema.py
trawler/sql/__init__.py
trawler/sql/extract.py
trawler/sql/metrics.py
trawler_python-0.0.2a3.dist-info/entry_points.txt
trawler_python-0.0.2a3.dist-info/LICENSE.md
trawler_python-0.0.2a3.dist-info/WHEEL
trawler_python-0.0.2a3.dist-info/METADATA
trawler_python-0.0.2a3.dist-info/RECORD
